autmux/__init__.py
autmux/console/__init__.py
autmux/console/cli.py
autmux/scenarios/__init__.py
autmux/scenarios/jobs/__init__.py
autmux/scenarios/jobs/do.py
autmux/scenarios/jobs/job.py
autmux/scenarios/jobs/send.py
autmux/scenarios/jobs/sleep.py
autmux/scenarios/jobs/tmux_exec.py
autmux/scenarios/scenario.py
autmux/tmux/__init__.py
autmux/tmux/config.py
autmux/tmux/tmux_client.py
autmux/tmux/utils.py
autmux-0.1.0.dist-info/entry_points.txt
autmux-0.1.0.dist-info/LICENSE
autmux-0.1.0.dist-info/WHEEL
autmux-0.1.0.dist-info/METADATA
autmux-0.1.0.dist-info/RECORD
