Metadata-Version: 2.1
Name: autmux
Version: 0.1.0
Summary: Automatically manipulating tmux
License: MIT
Author: Hiroki Konishi
Author-email: relastle@gmail.com
Requires-Python: >=3.6,<4.0
Classifier: License :: OSI Approved :: MIT License
Classifier: Programming Language :: Python :: 3
Classifier: Programming Language :: Python :: 3.6
Classifier: Programming Language :: Python :: 3.7
Classifier: Programming Language :: Python :: 3.8
Requires-Dist: PyYaml (>=5.3,<6.0)
Requires-Dist: click (>=7.0,<8.0)
Requires-Dist: click-help-colors (>=0.7,<0.8)
